{"config":{"output_file":null,"full_docs":false,"pub_only":false,"reachable_only":false,"distro_crate":false,"signatures":false,"borrow_data":false},"version":"0.19.0","compilation":{"directory":"/home/leef/proj/rust/minigrep","program":"/home/leef/.rustup/toolchains/stable-x86_64-unknown-linux-gnu/bin/rls","arguments":[],"output":"/home/leef/proj/rust/minigrep/target/rls/debug/deps/libminigrep-ae6f5ff4b19b81f3.rmeta"},"prelude":{"crate_id":{"name":"minigrep","disambiguator":[7860231644559306476,11681155485090806553]},"crate_root":"src","external_crates":[{"file_name":"/home/leef/proj/rust/minigrep/src/main.rs","num":1,"id":{"name":"std","disambiguator":[5726307116676674259,9254205407228129584]}},{"file_name":"/home/leef/proj/rust/minigrep/src/main.rs","num":2,"id":{"name":"core","disambiguator":[13299148613267607203,8249913267494127673]}},{"file_name":"/home/leef/proj/rust/minigrep/src/main.rs","num":3,"id":{"name":"compiler_builtins","disambiguator":[197050223691728347,13453459908300789634]}},{"file_name":"/home/leef/proj/rust/minigrep/src/main.rs","num":4,"id":{"name":"rustc_std_workspace_core","disambiguator":[7068544857341867760,4986237062560097230]}},{"file_name":"/home/leef/proj/rust/minigrep/src/main.rs","num":5,"id":{"name":"alloc","disambiguator":[18278181253470956455,5630036847974018351]}},{"file_name":"/home/leef/proj/rust/minigrep/src/main.rs","num":6,"id":{"name":"libc","disambiguator":[14314454188171778451,16107994531515979130]}},{"file_name":"/home/leef/proj/rust/minigrep/src/main.rs","num":7,"id":{"name":"unwind","disambiguator":[14027036961787401129,9740892787592816042]}},{"file_name":"/home/leef/proj/rust/minigrep/src/main.rs","num":8,"id":{"name":"hashbrown","disambiguator":[9151246664428058867,3149456407424329247]}},{"file_name":"/home/leef/proj/rust/minigrep/src/main.rs","num":9,"id":{"name":"rustc_std_workspace_alloc","disambiguator":[5378796546799943917,291117324214328413]}},{"file_name":"/home/leef/proj/rust/minigrep/src/main.rs","num":10,"id":{"name":"rustc_demangle","disambiguator":[14457926311222789857,2794564911830687161]}},{"file_name":"/home/leef/proj/rust/minigrep/src/main.rs","num":11,"id":{"name":"backtrace_sys","disambiguator":[16727297303745515064,14497453895406869387]}},{"file_name":"/home/leef/proj/rust/minigrep/src/main.rs","num":12,"id":{"name":"panic_unwind","disambiguator":[11013963231826958606,13465865664615988446]}}],"span":{"file_name":"src/main.rs","byte_start":0,"byte_end":2384,"line_start":1,"line_end":85,"column_start":1,"column_end":2}},"imports":[{"kind":"Use","ref_id":{"krate":1,"index":1396},"span":{"file_name":"src/main.rs","byte_start":9,"byte_end":12,"line_start":1,"line_end":1,"column_start":10,"column_end":13},"alias_span":null,"name":"env","value":"","parent":{"krate":0,"index":0}},{"kind":"Use","ref_id":{"krate":1,"index":1970},"span":{"file_name":"src/main.rs","byte_start":23,"byte_end":25,"line_start":2,"line_end":2,"column_start":10,"column_end":12},"alias_span":null,"name":"fs","value":"","parent":{"krate":0,"index":0}}],"defs":[{"kind":"Mod","id":{"krate":0,"index":0},"span":{"file_name":"src/main.rs","byte_start":0,"byte_end":2384,"line_start":1,"line_end":85,"column_start":1,"column_end":2},"name":"","qualname":"::","value":"src/main.rs","parent":null,"children":[{"krate":0,"index":10},{"krate":0,"index":11},{"krate":0,"index":12},{"krate":0,"index":13},{"krate":0,"index":14},{"krate":0,"index":15},{"krate":0,"index":16},{"krate":0,"index":17},{"krate":0,"index":23},{"krate":0,"index":30},{"krate":0,"index":18},{"krate":0,"index":19},{"krate":0,"index":20},{"krate":0,"index":21},{"krate":0,"index":22}],"decl_id":null,"docs":"","sig":null,"attributes":[]},{"kind":"Const","id":{"krate":0,"index":14},"span":{"file_name":"src/main.rs","byte_start":34,"byte_end":49,"line_start":4,"line_end":4,"column_start":7,"column_end":22},"name":"BRIGHTNESS_PATH","qualname":"::BRIGHTNESS_PATH","value":"&str","parent":null,"children":[],"decl_id":null,"docs":"","sig":null,"attributes":[]},{"kind":"Const","id":{"krate":0,"index":15},"span":{"file_name":"src/main.rs","byte_start":115,"byte_end":134,"line_start":5,"line_end":5,"column_start":7,"column_end":26},"name":"MAX_BRIGHTNESS_PATH","qualname":"::MAX_BRIGHTNESS_PATH","value":"&str","parent":null,"children":[],"decl_id":null,"docs":"","sig":null,"attributes":[]},{"kind":"Function","id":{"krate":0,"index":16},"span":{"file_name":"src/main.rs","byte_start":202,"byte_end":220,"line_start":7,"line_end":7,"column_start":4,"column_end":22},"name":"get_max_brightness","qualname":"::get_max_brightness","value":"fn () -> f32","parent":null,"children":[],"decl_id":null,"docs":"","sig":null,"attributes":[]},{"kind":"Local","id":{"krate":0,"index":4294967259},"span":{"file_name":"src/main.rs","byte_start":240,"byte_end":258,"line_start":8,"line_end":8,"column_start":9,"column_end":27},"name":"max_brightness_str","qualname":"max_brightness_str$36","value":"std::string::String","parent":null,"children":[],"decl_id":null,"docs":"","sig":null,"attributes":[]},{"kind":"Function","id":{"krate":0,"index":17},"span":{"file_name":"src/main.rs","byte_start":391,"byte_end":405,"line_start":12,"line_end":12,"column_start":4,"column_end":18},"name":"get_brightness","qualname":"::get_brightness","value":"fn () -> f32","parent":null,"children":[],"decl_id":null,"docs":"","sig":null,"attributes":[]},{"kind":"Local","id":{"krate":0,"index":4294967232},"span":{"file_name":"src/main.rs","byte_start":425,"byte_end":439,"line_start":13,"line_end":13,"column_start":9,"column_end":23},"name":"brightness_str","qualname":"brightness_str$63","value":"std::string::String","parent":null,"children":[],"decl_id":null,"docs":"","sig":null,"attributes":[]},{"kind":"TupleVariant","id":{"krate":0,"index":24},"span":{"file_name":"src/main.rs","byte_start":604,"byte_end":615,"line_start":19,"line_end":19,"column_start":5,"column_end":16},"name":"OutOfBounds","qualname":"::InputError::OutOfBounds","value":"InputError::OutOfBounds","parent":{"krate":0,"index":23},"children":[],"decl_id":null,"docs":"","sig":null,"attributes":[]},{"kind":"TupleVariant","id":{"krate":0,"index":26},"span":{"file_name":"src/main.rs","byte_start":621,"byte_end":633,"line_start":20,"line_end":20,"column_start":5,"column_end":17},"name":"NotAnInteger","qualname":"::InputError::NotAnInteger","value":"InputError::NotAnInteger","parent":{"krate":0,"index":23},"children":[],"decl_id":null,"docs":"","sig":null,"attributes":[]},{"kind":"TupleVariant","id":{"krate":0,"index":28},"span":{"file_name":"src/main.rs","byte_start":639,"byte_end":650,"line_start":21,"line_end":21,"column_start":5,"column_end":16},"name":"TooManyArgs","qualname":"::InputError::TooManyArgs","value":"InputError::TooManyArgs","parent":{"krate":0,"index":23},"children":[],"decl_id":null,"docs":"","sig":null,"attributes":[]},{"kind":"Enum","id":{"krate":0,"index":23},"span":{"file_name":"src/main.rs","byte_start":587,"byte_end":597,"line_start":18,"line_end":18,"column_start":10,"column_end":20},"name":"InputError","qualname":"::InputError","value":"InputError::{OutOfBounds, NotAnInteger, TooManyArgs}","parent":null,"children":[{"krate":0,"index":24},{"krate":0,"index":26},{"krate":0,"index":28}],"decl_id":null,"docs":"","sig":null,"attributes":[]},{"kind":"Local","id":{"krate":0,"index":4294967209},"span":{"file_name":"src/main.rs","byte_start":668,"byte_end":669,"line_start":24,"line_end":24,"column_start":14,"column_end":15},"name":"t","qualname":"::get_delta::t","value":"&str","parent":null,"children":[],"decl_id":null,"docs":"","sig":null,"attributes":[]},{"kind":"Function","id":{"krate":0,"index":18},"span":{"file_name":"src/main.rs","byte_start":658,"byte_end":667,"line_start":24,"line_end":24,"column_start":4,"column_end":13},"name":"get_delta","qualname":"::get_delta","value":"fn (t: &str) -> Result<i32, InputError>","parent":null,"children":[],"decl_id":null,"docs":"","sig":null,"attributes":[]},{"kind":"Local","id":{"krate":0,"index":4294967196},"span":{"file_name":"src/main.rs","byte_start":714,"byte_end":720,"line_start":25,"line_end":25,"column_start":9,"column_end":15},"name":"result","qualname":"result$99","value":"std::result::Result<f32, std::num::ParseFloatError>","parent":null,"children":[],"decl_id":null,"docs":"","sig":null,"attributes":[]},{"kind":"Local","id":{"krate":0,"index":4294967182},"span":{"file_name":"src/main.rs","byte_start":771,"byte_end":772,"line_start":26,"line_end":26,"column_start":15,"column_end":16},"name":"i","qualname":"i$113","value":"f32","parent":null,"children":[],"decl_id":null,"docs":"","sig":null,"attributes":[]},{"kind":"Local","id":{"krate":0,"index":4294967159},"span":{"file_name":"src/main.rs","byte_start":902,"byte_end":905,"line_start":30,"line_end":30,"column_start":17,"column_end":20},"name":"rat","qualname":"rat$136","value":"f32","parent":null,"children":[],"decl_id":null,"docs":"","sig":null,"attributes":[]},{"kind":"Local","id":{"krate":0,"index":4294967153},"span":{"file_name":"src/main.rs","byte_start":935,"byte_end":943,"line_start":31,"line_end":31,"column_start":17,"column_end":25},"name":"bright_d","qualname":"bright_d$142","value":"f32","parent":null,"children":[],"decl_id":null,"docs":"","sig":null,"attributes":[]},{"kind":"Local","id":{"krate":0,"index":4294967121},"span":{"file_name":"src/main.rs","byte_start":1191,"byte_end":1192,"line_start":40,"line_end":40,"column_start":19,"column_end":20},"name":"t","qualname":"::add_brightness::t","value":"i32","parent":null,"children":[],"decl_id":null,"docs":"","sig":null,"attributes":[]},{"kind":"Function","id":{"krate":0,"index":19},"span":{"file_name":"src/main.rs","byte_start":1176,"byte_end":1190,"line_start":40,"line_end":40,"column_start":4,"column_end":18},"name":"add_brightness","qualname":"::add_brightness","value":"fn (t: i32) -> ()","parent":null,"children":[],"decl_id":null,"docs":"","sig":null,"attributes":[]},{"kind":"Local","id":{"krate":0,"index":4294967114},"span":{"file_name":"src/main.rs","byte_start":1259,"byte_end":1260,"line_start":44,"line_end":44,"column_start":19,"column_end":20},"name":"t","qualname":"::sub_brightness::t","value":"i32","parent":null,"children":[],"decl_id":null,"docs":"","sig":null,"attributes":[]},{"kind":"Function","id":{"krate":0,"index":20},"span":{"file_name":"src/main.rs","byte_start":1244,"byte_end":1258,"line_start":44,"line_end":44,"column_start":4,"column_end":18},"name":"sub_brightness","qualname":"::sub_brightness","value":"fn (t: i32) -> ()","parent":null,"children":[],"decl_id":null,"docs":"","sig":null,"attributes":[]},{"kind":"Local","id":{"krate":0,"index":4294967107},"span":{"file_name":"src/main.rs","byte_start":1322,"byte_end":1323,"line_start":48,"line_end":48,"column_start":19,"column_end":20},"name":"t","qualname":"::set_brightness::t","value":"i32","parent":null,"children":[],"decl_id":null,"docs":"","sig":null,"attributes":[]},{"kind":"Function","id":{"krate":0,"index":21},"span":{"file_name":"src/main.rs","byte_start":1307,"byte_end":1321,"line_start":48,"line_end":48,"column_start":4,"column_end":18},"name":"set_brightness","qualname":"::set_brightness","value":"fn (t: i32) -> ()","parent":null,"children":[],"decl_id":null,"docs":"","sig":null,"attributes":[]},{"kind":"Function","id":{"krate":0,"index":22},"span":{"file_name":"src/main.rs","byte_start":1421,"byte_end":1425,"line_start":53,"line_end":53,"column_start":4,"column_end":8},"name":"main","qualname":"::main","value":"fn () -> ()","parent":null,"children":[],"decl_id":null,"docs":"","sig":null,"attributes":[]},{"kind":"Local","id":{"krate":0,"index":4294967086},"span":{"file_name":"src/main.rs","byte_start":1438,"byte_end":1442,"line_start":54,"line_end":54,"column_start":9,"column_end":13},"name":"args","qualname":"args$209","value":"std::vec::Vec<std::string::String>","parent":null,"children":[],"decl_id":null,"docs":"","sig":null,"attributes":[]},{"kind":"Local","id":{"krate":0,"index":4294967074},"span":{"file_name":"src/main.rs","byte_start":1489,"byte_end":1494,"line_start":55,"line_end":55,"column_start":9,"column_end":14},"name":"query","qualname":"query$221","value":"&std::string::String","parent":null,"children":[],"decl_id":null,"docs":"","sig":null,"attributes":[]},{"kind":"Local","id":{"krate":0,"index":4294967067},"span":{"file_name":"src/main.rs","byte_start":1515,"byte_end":1528,"line_start":56,"line_end":56,"column_start":9,"column_end":22},"name":"current_ratio","qualname":"current_ratio$228","value":"f32","parent":null,"children":[],"decl_id":null,"docs":"","sig":null,"attributes":[]},{"kind":"Local","id":{"krate":0,"index":4294967052},"span":{"file_name":"src/main.rs","byte_start":1828,"byte_end":1838,"line_start":67,"line_end":67,"column_start":13,"column_end":23},"name":"first_char","qualname":"first_char$243","value":"&str","parent":null,"children":[],"decl_id":null,"docs":"","sig":null,"attributes":[]},{"kind":"Local","id":{"krate":0,"index":4294967043},"span":{"file_name":"src/main.rs","byte_start":1867,"byte_end":1875,"line_start":68,"line_end":68,"column_start":13,"column_end":21},"name":"the_rest","qualname":"the_rest$252","value":"&str","parent":null,"children":[],"decl_id":null,"docs":"","sig":null,"attributes":[]},{"kind":"Local","id":{"krate":0,"index":4294967031},"span":{"file_name":"src/main.rs","byte_start":1969,"byte_end":1977,"line_start":70,"line_end":70,"column_start":13,"column_end":21},"name":"bright_d","qualname":"bright_d$264","value":"std::result::Result<i32, InputError>","parent":null,"children":[],"decl_id":null,"docs":"","sig":null,"attributes":[]},{"kind":"Local","id":{"krate":0,"index":4294967003},"span":{"file_name":"src/main.rs","byte_start":2153,"byte_end":2154,"line_start":76,"line_end":76,"column_start":16,"column_end":17},"name":"d","qualname":"d$292","value":"i32","parent":null,"children":[],"decl_id":null,"docs":"","sig":null,"attributes":[]},{"kind":"Local","id":{"krate":0,"index":4294966977},"span":{"file_name":"src/main.rs","byte_start":2334,"byte_end":2335,"line_start":82,"line_end":82,"column_start":17,"column_end":18},"name":"e","qualname":"e$318","value":"InputError","parent":null,"children":[],"decl_id":null,"docs":"","sig":null,"attributes":[]}],"impls":[],"refs":[{"kind":"Mod","span":{"file_name":"src/main.rs","byte_start":4,"byte_end":7,"line_start":1,"line_end":1,"column_start":5,"column_end":8},"ref_id":{"krate":1,"index":0}},{"kind":"Mod","span":{"file_name":"src/main.rs","byte_start":18,"byte_end":21,"line_start":2,"line_end":2,"column_start":5,"column_end":8},"ref_id":{"krate":1,"index":0}},{"kind":"Function","span":{"file_name":"src/main.rs","byte_start":301,"byte_end":307,"line_start":8,"line_end":8,"column_start":70,"column_end":76},"ref_id":{"krate":2,"index":4593}},{"kind":"Function","span":{"file_name":"src/main.rs","byte_start":265,"byte_end":279,"line_start":8,"line_end":8,"column_start":34,"column_end":48},"ref_id":{"krate":1,"index":2002}},{"kind":"Mod","span":{"file_name":"src/main.rs","byte_start":261,"byte_end":263,"line_start":8,"line_end":8,"column_start":30,"column_end":32},"ref_id":{"krate":1,"index":1970}},{"kind":"Variable","span":{"file_name":"src/main.rs","byte_start":280,"byte_end":299,"line_start":8,"line_end":8,"column_start":49,"column_end":68},"ref_id":{"krate":0,"index":15}},{"kind":"Function","span":{"file_name":"src/main.rs","byte_start":375,"byte_end":381,"line_start":9,"line_end":9,"column_start":53,"column_end":59},"ref_id":{"krate":2,"index":4592}},{"kind":"Function","span":{"file_name":"src/main.rs","byte_start":360,"byte_end":365,"line_start":9,"line_end":9,"column_start":38,"column_end":43},"ref_id":{"krate":2,"index":6261}},{"kind":"Function","span":{"file_name":"src/main.rs","byte_start":353,"byte_end":357,"line_start":9,"line_end":9,"column_start":31,"column_end":35},"ref_id":{"krate":2,"index":6238}},{"kind":"Variable","span":{"file_name":"src/main.rs","byte_start":334,"byte_end":352,"line_start":9,"line_end":9,"column_start":12,"column_end":30},"ref_id":{"krate":0,"index":4294967259}},{"kind":"Function","span":{"file_name":"src/main.rs","byte_start":478,"byte_end":484,"line_start":13,"line_end":13,"column_start":62,"column_end":68},"ref_id":{"krate":2,"index":4593}},{"kind":"Function","span":{"file_name":"src/main.rs","byte_start":446,"byte_end":460,"line_start":13,"line_end":13,"column_start":30,"column_end":44},"ref_id":{"krate":1,"index":2002}},{"kind":"Mod","span":{"file_name":"src/main.rs","byte_start":442,"byte_end":444,"line_start":13,"line_end":13,"column_start":26,"column_end":28},"ref_id":{"krate":1,"index":1970}},{"kind":"Variable","span":{"file_name":"src/main.rs","byte_start":461,"byte_end":476,"line_start":13,"line_end":13,"column_start":45,"column_end":60},"ref_id":{"krate":0,"index":14}},{"kind":"Function","span":{"file_name":"src/main.rs","byte_start":548,"byte_end":554,"line_start":14,"line_end":14,"column_start":49,"column_end":55},"ref_id":{"krate":2,"index":4592}},{"kind":"Function","span":{"file_name":"src/main.rs","byte_start":533,"byte_end":538,"line_start":14,"line_end":14,"column_start":34,"column_end":39},"ref_id":{"krate":2,"index":6261}},{"kind":"Function","span":{"file_name":"src/main.rs","byte_start":526,"byte_end":530,"line_start":14,"line_end":14,"column_start":27,"column_end":31},"ref_id":{"krate":2,"index":6238}},{"kind":"Variable","span":{"file_name":"src/main.rs","byte_start":511,"byte_end":525,"line_start":14,"line_end":14,"column_start":12,"column_end":26},"ref_id":{"krate":0,"index":4294967232}},{"kind":"Type","span":{"file_name":"src/main.rs","byte_start":680,"byte_end":686,"line_start":24,"line_end":24,"column_start":26,"column_end":32},"ref_id":{"krate":2,"index":32805}},{"kind":"Type","span":{"file_name":"src/main.rs","byte_start":692,"byte_end":702,"line_start":24,"line_end":24,"column_start":38,"column_end":48},"ref_id":{"krate":0,"index":23}},{"kind":"Type","span":{"file_name":"src/main.rs","byte_start":722,"byte_end":728,"line_start":25,"line_end":25,"column_start":17,"column_end":23},"ref_id":{"krate":2,"index":32805}},{"kind":"Function","span":{"file_name":"src/main.rs","byte_start":741,"byte_end":746,"line_start":25,"line_end":25,"column_start":36,"column_end":41},"ref_id":{"krate":2,"index":6261}},{"kind":"Variable","span":{"file_name":"src/main.rs","byte_start":739,"byte_end":740,"line_start":25,"line_end":25,"column_start":34,"column_end":35},"ref_id":{"krate":0,"index":4294967209}},{"kind":"Variable","span":{"file_name":"src/main.rs","byte_start":768,"byte_end":770,"line_start":26,"line_end":26,"column_start":12,"column_end":14},"ref_id":{"krate":2,"index":32809}},{"kind":"Variable","span":{"file_name":"src/main.rs","byte_start":768,"byte_end":770,"line_start":26,"line_end":26,"column_start":12,"column_end":14},"ref_id":{"krate":2,"index":32809}},{"kind":"Variable","span":{"file_name":"src/main.rs","byte_start":776,"byte_end":782,"line_start":26,"line_end":26,"column_start":20,"column_end":26},"ref_id":{"krate":0,"index":4294967196}},{"kind":"Variable","span":{"file_name":"src/main.rs","byte_start":796,"byte_end":797,"line_start":27,"line_end":27,"column_start":12,"column_end":13},"ref_id":{"krate":0,"index":4294967182}},{"kind":"Variable","span":{"file_name":"src/main.rs","byte_start":809,"byte_end":810,"line_start":27,"line_end":27,"column_start":25,"column_end":26},"ref_id":{"krate":0,"index":4294967182}},{"kind":"Variable","span":{"file_name":"src/main.rs","byte_start":839,"byte_end":842,"line_start":28,"line_end":28,"column_start":20,"column_end":23},"ref_id":{"krate":2,"index":32812}},{"kind":"Variable","span":{"file_name":"src/main.rs","byte_start":855,"byte_end":866,"line_start":28,"line_end":28,"column_start":36,"column_end":47},"ref_id":{"krate":0,"index":25}},{"kind":"Type","span":{"file_name":"src/main.rs","byte_start":843,"byte_end":853,"line_start":28,"line_end":28,"column_start":24,"column_end":34},"ref_id":{"krate":0,"index":23}},{"kind":"Variable","span":{"file_name":"src/main.rs","byte_start":908,"byte_end":909,"line_start":30,"line_end":30,"column_start":23,"column_end":24},"ref_id":{"krate":0,"index":4294967182}},{"kind":"Variable","span":{"file_name":"src/main.rs","byte_start":946,"byte_end":949,"line_start":31,"line_end":31,"column_start":28,"column_end":31},"ref_id":{"krate":0,"index":4294967159}},{"kind":"Function","span":{"file_name":"src/main.rs","byte_start":952,"byte_end":970,"line_start":31,"line_end":31,"column_start":34,"column_end":52},"ref_id":{"krate":0,"index":16}},{"kind":"Variable","span":{"file_name":"src/main.rs","byte_start":1031,"byte_end":1034,"line_start":32,"line_end":32,"column_start":58,"column_end":61},"ref_id":{"krate":0,"index":4294967159}},{"kind":"Variable","span":{"file_name":"src/main.rs","byte_start":1036,"byte_end":1044,"line_start":32,"line_end":32,"column_start":63,"column_end":71},"ref_id":{"krate":0,"index":4294967153}},{"kind":"Variable","span":{"file_name":"src/main.rs","byte_start":1066,"byte_end":1068,"line_start":33,"line_end":33,"column_start":20,"column_end":22},"ref_id":{"krate":2,"index":32809}},{"kind":"Function","span":{"file_name":"src/main.rs","byte_start":1078,"byte_end":1083,"line_start":33,"line_end":33,"column_start":32,"column_end":37},"ref_id":{"krate":1,"index":155}},{"kind":"Variable","span":{"file_name":"src/main.rs","byte_start":1069,"byte_end":1077,"line_start":33,"line_end":33,"column_start":23,"column_end":31},"ref_id":{"krate":0,"index":4294967153}},{"kind":"Variable","span":{"file_name":"src/main.rs","byte_start":1133,"byte_end":1136,"line_start":36,"line_end":36,"column_start":16,"column_end":19},"ref_id":{"krate":2,"index":32812}},{"kind":"Variable","span":{"file_name":"src/main.rs","byte_start":1149,"byte_end":1161,"line_start":36,"line_end":36,"column_start":32,"column_end":44},"ref_id":{"krate":0,"index":27}},{"kind":"Type","span":{"file_name":"src/main.rs","byte_start":1137,"byte_end":1147,"line_start":36,"line_end":36,"column_start":20,"column_end":30},"ref_id":{"krate":0,"index":23}},{"kind":"Variable","span":{"file_name":"src/main.rs","byte_start":1234,"byte_end":1235,"line_start":41,"line_end":41,"column_start":34,"column_end":35},"ref_id":{"krate":0,"index":4294967121}},{"kind":"Variable","span":{"file_name":"src/main.rs","byte_start":1297,"byte_end":1298,"line_start":45,"line_end":45,"column_start":29,"column_end":30},"ref_id":{"krate":0,"index":4294967114}},{"kind":"Variable","span":{"file_name":"src/main.rs","byte_start":1355,"byte_end":1356,"line_start":49,"line_end":49,"column_start":24,"column_end":25},"ref_id":{"krate":0,"index":4294967107}},{"kind":"Function","span":{"file_name":"src/main.rs","byte_start":1405,"byte_end":1411,"line_start":50,"line_end":50,"column_start":47,"column_end":53},"ref_id":{"krate":2,"index":4592}},{"kind":"Function","span":{"file_name":"src/main.rs","byte_start":1367,"byte_end":1372,"line_start":50,"line_end":50,"column_start":9,"column_end":14},"ref_id":{"krate":1,"index":2005}},{"kind":"Mod","span":{"file_name":"src/main.rs","byte_start":1363,"byte_end":1365,"line_start":50,"line_end":50,"column_start":5,"column_end":7},"ref_id":{"krate":1,"index":1970}},{"kind":"Variable","span":{"file_name":"src/main.rs","byte_start":1373,"byte_end":1388,"line_start":50,"line_end":50,"column_start":15,"column_end":30},"ref_id":{"krate":0,"index":14}},{"kind":"Function","span":{"file_name":"src/main.rs","byte_start":1392,"byte_end":1401,"line_start":50,"line_end":50,"column_start":34,"column_end":43},"ref_id":{"krate":5,"index":3453}},{"kind":"Variable","span":{"file_name":"src/main.rs","byte_start":1390,"byte_end":1391,"line_start":50,"line_end":50,"column_start":32,"column_end":33},"ref_id":{"krate":0,"index":4294967107}},{"kind":"Type","span":{"file_name":"src/main.rs","byte_start":1444,"byte_end":1447,"line_start":54,"line_end":54,"column_start":15,"column_end":18},"ref_id":{"krate":5,"index":3563}},{"kind":"Type","span":{"file_name":"src/main.rs","byte_start":1448,"byte_end":1454,"line_start":54,"line_end":54,"column_start":19,"column_end":25},"ref_id":{"krate":5,"index":4679}},{"kind":"Function","span":{"file_name":"src/main.rs","byte_start":1470,"byte_end":1477,"line_start":54,"line_end":54,"column_start":41,"column_end":48},"ref_id":{"krate":2,"index":3188}},{"kind":"Function","span":{"file_name":"src/main.rs","byte_start":1463,"byte_end":1467,"line_start":54,"line_end":54,"column_start":34,"column_end":38},"ref_id":{"krate":1,"index":1477}},{"kind":"Mod","span":{"file_name":"src/main.rs","byte_start":1458,"byte_end":1461,"line_start":54,"line_end":54,"column_start":29,"column_end":32},"ref_id":{"krate":1,"index":1396}},{"kind":"Variable","span":{"file_name":"src/main.rs","byte_start":1498,"byte_end":1502,"line_start":55,"line_end":55,"column_start":18,"column_end":22},"ref_id":{"krate":0,"index":4294967086}},{"kind":"Function","span":{"file_name":"src/main.rs","byte_start":1531,"byte_end":1545,"line_start":56,"line_end":56,"column_start":25,"column_end":39},"ref_id":{"krate":0,"index":17}},{"kind":"Function","span":{"file_name":"src/main.rs","byte_start":1550,"byte_end":1568,"line_start":56,"line_end":56,"column_start":44,"column_end":62},"ref_id":{"krate":0,"index":16}},{"kind":"Function","span":{"file_name":"src/main.rs","byte_start":1654,"byte_end":1668,"line_start":59,"line_end":59,"column_start":9,"column_end":23},"ref_id":{"krate":0,"index":17}},{"kind":"Function","span":{"file_name":"src/main.rs","byte_start":1680,"byte_end":1698,"line_start":60,"line_end":60,"column_start":9,"column_end":27},"ref_id":{"krate":0,"index":16}},{"kind":"Variable","span":{"file_name":"src/main.rs","byte_start":1710,"byte_end":1723,"line_start":61,"line_end":61,"column_start":9,"column_end":22},"ref_id":{"krate":0,"index":4294967067}},{"kind":"Variable","span":{"file_name":"src/main.rs","byte_start":1739,"byte_end":1744,"line_start":64,"line_end":64,"column_start":8,"column_end":13},"ref_id":{"krate":0,"index":4294967074}},{"kind":"Variable","span":{"file_name":"src/main.rs","byte_start":1842,"byte_end":1847,"line_start":67,"line_end":67,"column_start":27,"column_end":32},"ref_id":{"krate":0,"index":4294967074}},{"kind":"Variable","span":{"file_name":"src/main.rs","byte_start":1879,"byte_end":1884,"line_start":68,"line_end":68,"column_start":25,"column_end":30},"ref_id":{"krate":0,"index":4294967074}},{"kind":"Function","span":{"file_name":"src/main.rs","byte_start":1894,"byte_end":1897,"line_start":68,"line_end":68,"column_start":40,"column_end":43},"ref_id":{"krate":5,"index":3328}},{"kind":"Variable","span":{"file_name":"src/main.rs","byte_start":1888,"byte_end":1893,"line_start":68,"line_end":68,"column_start":34,"column_end":39},"ref_id":{"krate":0,"index":4294967074}},{"kind":"Variable","span":{"file_name":"src/main.rs","byte_start":1983,"byte_end":1993,"line_start":70,"line_end":70,"column_start":27,"column_end":37},"ref_id":{"krate":0,"index":4294967052}},{"kind":"Variable","span":{"file_name":"src/main.rs","byte_start":2004,"byte_end":2014,"line_start":70,"line_end":70,"column_start":48,"column_end":58},"ref_id":{"krate":0,"index":4294967052}},{"kind":"Function","span":{"file_name":"src/main.rs","byte_start":2036,"byte_end":2045,"line_start":71,"line_end":71,"column_start":13,"column_end":22},"ref_id":{"krate":0,"index":18}},{"kind":"Variable","span":{"file_name":"src/main.rs","byte_start":2046,"byte_end":2054,"line_start":71,"line_end":71,"column_start":23,"column_end":31},"ref_id":{"krate":0,"index":4294967043}},{"kind":"Function","span":{"file_name":"src/main.rs","byte_start":2085,"byte_end":2094,"line_start":73,"line_end":73,"column_start":13,"column_end":22},"ref_id":{"krate":0,"index":18}},{"kind":"Variable","span":{"file_name":"src/main.rs","byte_start":2095,"byte_end":2100,"line_start":73,"line_end":73,"column_start":23,"column_end":28},"ref_id":{"krate":0,"index":4294967074}},{"kind":"Variable","span":{"file_name":"src/main.rs","byte_start":2127,"byte_end":2135,"line_start":75,"line_end":75,"column_start":15,"column_end":23},"ref_id":{"krate":0,"index":4294967031}},{"kind":"Variable","span":{"file_name":"src/main.rs","byte_start":2150,"byte_end":2152,"line_start":76,"line_end":76,"column_start":13,"column_end":15},"ref_id":{"krate":2,"index":32809}},{"kind":"Variable","span":{"file_name":"src/main.rs","byte_start":2150,"byte_end":2152,"line_start":76,"line_end":76,"column_start":13,"column_end":15},"ref_id":{"krate":2,"index":32809}},{"kind":"Variable","span":{"file_name":"src/main.rs","byte_start":2165,"byte_end":2175,"line_start":76,"line_end":76,"column_start":28,"column_end":38},"ref_id":{"krate":0,"index":4294967052}},{"kind":"Function","span":{"file_name":"src/main.rs","byte_start":2201,"byte_end":2215,"line_start":77,"line_end":77,"column_start":24,"column_end":38},"ref_id":{"krate":0,"index":19}},{"kind":"Variable","span":{"file_name":"src/main.rs","byte_start":2216,"byte_end":2217,"line_start":77,"line_end":77,"column_start":39,"column_end":40},"ref_id":{"krate":0,"index":4294967003}},{"kind":"Function","span":{"file_name":"src/main.rs","byte_start":2243,"byte_end":2257,"line_start":78,"line_end":78,"column_start":24,"column_end":38},"ref_id":{"krate":0,"index":20}},{"kind":"Variable","span":{"file_name":"src/main.rs","byte_start":2258,"byte_end":2259,"line_start":78,"line_end":78,"column_start":39,"column_end":40},"ref_id":{"krate":0,"index":4294967003}},{"kind":"Function","span":{"file_name":"src/main.rs","byte_start":2283,"byte_end":2297,"line_start":79,"line_end":79,"column_start":22,"column_end":36},"ref_id":{"krate":0,"index":21}},{"kind":"Variable","span":{"file_name":"src/main.rs","byte_start":2298,"byte_end":2299,"line_start":79,"line_end":79,"column_start":37,"column_end":38},"ref_id":{"krate":0,"index":4294967003}},{"kind":"Variable","span":{"file_name":"src/main.rs","byte_start":2330,"byte_end":2333,"line_start":82,"line_end":82,"column_start":13,"column_end":16},"ref_id":{"krate":2,"index":32812}},{"kind":"Variable","span":{"file_name":"src/main.rs","byte_start":2330,"byte_end":2333,"line_start":82,"line_end":82,"column_start":13,"column_end":16},"ref_id":{"krate":2,"index":32812}},{"kind":"Variable","span":{"file_name":"src/main.rs","byte_start":2363,"byte_end":2364,"line_start":82,"line_end":82,"column_start":46,"column_end":47},"ref_id":{"krate":0,"index":4294966977}}],"macro_refs":[],"relations":[]}